viz/__init__.py
viz/version.py
viz/generators/__init__.py
viz/generators/c0dtlz2.py
viz/generators/c2dtlz2.py
viz/generators/cdebmdk.py
viz/generators/debmdk.py
viz/generators/dtlz2.py
viz/generators/dtlz8.py
viz/plotting/__init__.py
viz/plotting/paletteviz.py
viz/plotting/pcp.py
viz/plotting/radviz.py
viz/plotting/scatter.py
viz/plotting/star.py
viz/plotting/utils.py
viz/tda/__init__.py
viz/tda/simple_shape.py
viz/utils/__init__.py
viz/utils/dm.py
viz/utils/io.py
viz/utils/sampling.py
viz/utils/transform.py
viz/utils/tests/__init__.py
viz/utils/tests/test_dm.py
viz/utils/tests/test_io.py
pviz-0.1.0rc16.dist-info/LICENSE
pviz-0.1.0rc16.dist-info/METADATA
pviz-0.1.0rc16.dist-info/WHEEL
pviz-0.1.0rc16.dist-info/top_level.txt
pviz-0.1.0rc16.dist-info/RECORD
