Metadata-Version: 2.1
Name: pviz
Version: 0.1.0rc16
Summary: A framework for high-dimensional (3 <= m <= 10) Pareto-optimal front visualization and analytics
Home-page: https://github.com/chudur-budur/pviz
Author: AKM Khaled Talukder
Author-email: talukde1@msu.edu
License: Apache-2.0
Platform: UNKNOWN
Classifier: Development Status :: 2 - Pre-Alpha
Classifier: Intended Audience :: Science/Research
Classifier: Programming Language :: Python :: 3.9
Requires-Dist: scipy (==1.6.0)
Requires-Dist: matplotlib
